herbie_core/__init__.py
herbie_core/apps.py
herbie_core/constants.py
herbie_core/urls.py
herbie_core/admin/__init__.py
herbie_core/admin/business_entity.py
herbie_core/admin/json_schema.py
herbie_core/authentication/social_authentication.py
herbie_core/exceptions/__init__.py
herbie_core/exceptions/invalid_messaging_provider.py
herbie_core/initializers/__init__.py
herbie_core/initializers/abstract_initializer.py
herbie_core/initializers/permisson_initializer.py
herbie_core/initializers/schema_initializer.py
herbie_core/management/__init__.py
herbie_core/management/commands/__init__.py
herbie_core/management/commands/export_data.py
herbie_core/management/commands/generatemodels.py
herbie_core/management/commands/import_json_schemas.py
herbie_core/management/commands/init_db.py
herbie_core/migrations/0001_initial.py
herbie_core/migrations/__init__.py
herbie_core/models/__init__.py
herbie_core/models/generated_models.py
herbie_core/models/message_models_and_serializers.py
herbie_core/models/models.py
herbie_core/models/schema.py
herbie_core/serializers/__init__.py
herbie_core/serializers/business_entity_serializer.py
herbie_core/services/__init__.py
herbie_core/services/business_entity_manager.py
herbie_core/services/json_schema_validator.py
herbie_core/services/permission_manager.py
herbie_core/services/schema_importer.py
herbie_core/services/schema_package.py
herbie_core/services/schema_registry.py
herbie_core/services/schema_version_compatibility.py
herbie_core/services/utils.py
herbie_core/services/message_publisher/__init__.py
herbie_core/services/message_publisher/abstract_publisher.py
herbie_core/services/message_publisher/logging_publisher.py
herbie_core/services/message_publisher/message_publisher.py
herbie_core/services/message_publisher/registry.py
herbie_core/services/schema_mock_data/__init__.py
herbie_core/services/schema_mock_data/schema_array_generator.py
herbie_core/services/schema_mock_data/schema_boolean_generator.py
herbie-1.0b2.dist-info/LICENSE
herbie-1.0b2.dist-info/METADATA
herbie-1.0b2.dist-info/WHEEL
herbie-1.0b2.dist-info/top_level.txt
herbie-1.0b2.dist-info/RECORD
