Metadata-Version: 2.1
Name: herbie
Version: 1.0b2
Summary: Herbie is a central data store for business data in a distributed service architecture.
Home-page: https://github.com/herbie/herbie
Author: Project A Services GmbH & Co. KG
Author-email: herbie@project-a.com
License: MIT
Platform: UNKNOWN
Classifier: Programming Language :: Python :: 3.6
Classifier: Programming Language :: Python :: 3.7
Classifier: Programming Language :: Python :: 3.8
Classifier: Framework :: Django :: 3.0
Classifier: Framework :: Django :: 3.1
Classifier: License :: OSI Approved :: MIT License
Classifier: Operating System :: OS Independent
Requires-Python: >=3.6
Requires-Dist: django (<4.0,>=3.0)
Requires-Dist: django-environ (>=0.4)
Requires-Dist: django-model-utils (>=4.0)
Requires-Dist: djangorestframework (<4.0,>=3.11)
Requires-Dist: jsonschema (>=3.2)
Requires-Dist: psycopg2 (>=2.8)
Requires-Dist: strict-rfc3339 (<1.0,>=0.7)
Provides-Extra: dev
Requires-Dist: twine ; extra == 'dev'
Provides-Extra: social_login
Requires-Dist: social-auth-app-django (==3.1.0) ; extra == 'social_login'
Provides-Extra: tests
Requires-Dist: pytest (<6.0,>=5.4.3) ; extra == 'tests'
Requires-Dist: pytest-django (<4.0,>=3.7.0) ; extra == 'tests'
Requires-Dist: flake8 (>=3.8.0) ; extra == 'tests'
Requires-Dist: black (==19.10b0) ; extra == 'tests'
Requires-Dist: Faker (==4.1.2) ; extra == 'tests'
Requires-Dist: rstr (==2.2.6) ; extra == 'tests'
